gismap/__init__.py
gismap/author.py
gismap/gismap.py
gismap/gismo.py
gismap/search.py
gismap/lab/__init__.py
gismap/lab/egomap.py
gismap/lab/expansion.py
gismap/lab/filters.py
gismap/lab/graph.py
gismap/lab/lab_author.py
gismap/lab/labmap.py
gismap/lab/lincs.py
gismap/lab/lip6.py
gismap/lab/toulouse.py
gismap/lab/vis.py
gismap/sources/__init__.py
gismap/sources/dblp.py
gismap/sources/hal.py
gismap/sources/models.py
gismap/sources/multi.py
gismap/utils/__init__.py
gismap/utils/common.py
gismap/utils/logger.py
gismap/utils/requests.py
gismap/utils/text.py
gismap-0.2.2.dist-info/METADATA
gismap-0.2.2.dist-info/WHEEL
gismap-0.2.2.dist-info/licenses/AUTHORS.md
gismap-0.2.2.dist-info/RECORD
