Metadata-Version: 2.4
Name: gismap
Version: 0.2.2
Summary: GISMAP leverages DBLP and HAL databases to provide cartography tools for you and your lab.
Project-URL: Repository, https://github.com/balouf/gismap
Project-URL: Documentation, https://balouf.github.io/gismap
Author-email: Fabien Mathieu <fabien.mathieu@normalesup.org>
Maintainer-email: Fabien Mathieu <fabien.mathieu@normalesup.org>
License-Expression: MIT
License-File: AUTHORS.md
Requires-Python: >=3.10
Requires-Dist: bof>=0.3.5
Requires-Dist: gismo>=0.5.2
Requires-Dist: ipykernel>=6.30.1
Requires-Dist: tqdm>=4.67.1
